django_import_export-4.3.11.dist-info/licenses/AUTHORS
django_import_export-4.3.11.dist-info/licenses/LICENSE
import_export/__init__.py
import_export/_version.py
import_export/admin.py
import_export/command_utils.py
import_export/declarative.py
import_export/exceptions.py
import_export/fields.py
import_export/forms.py
import_export/instance_loaders.py
import_export/mixins.py
import_export/options.py
import_export/resources.py
import_export/results.py
import_export/signals.py
import_export/tmp_storages.py
import_export/utils.py
import_export/widgets.py
import_export/formats/__init__.py
import_export/formats/base_formats.py
import_export/locale/ar/LC_MESSAGES/django.mo
import_export/locale/ar/LC_MESSAGES/django.po
import_export/locale/bg/LC_MESSAGES/django.mo
import_export/locale/bg/LC_MESSAGES/django.po
import_export/locale/ca/LC_MESSAGES/django.mo
import_export/locale/ca/LC_MESSAGES/django.po
import_export/locale/cs/LC_MESSAGES/django.mo
import_export/locale/cs/LC_MESSAGES/django.po
import_export/locale/de/LC_MESSAGES/django.mo
import_export/locale/de/LC_MESSAGES/django.po
import_export/locale/es/LC_MESSAGES/django.mo
import_export/locale/es/LC_MESSAGES/django.po
import_export/locale/es_AR/LC_MESSAGES/django.mo
import_export/locale/es_AR/LC_MESSAGES/django.po
import_export/locale/fa/LC_MESSAGES/django.mo
import_export/locale/fa/LC_MESSAGES/django.po
import_export/locale/fi/LC_MESSAGES/django.mo
import_export/locale/fi/LC_MESSAGES/django.po
import_export/locale/fr/LC_MESSAGES/django.mo
import_export/locale/fr/LC_MESSAGES/django.po
import_export/locale/he/LC_MESSAGES/django.mo
import_export/locale/he/LC_MESSAGES/django.po
import_export/locale/it/LC_MESSAGES/django.mo
import_export/locale/it/LC_MESSAGES/django.po
import_export/locale/ja/LC_MESSAGES/django.mo
import_export/locale/ja/LC_MESSAGES/django.po
import_export/locale/ko/LC_MESSAGES/django.mo
import_export/locale/ko/LC_MESSAGES/django.po
import_export/locale/kz/LC_MESSAGES/django.mo
import_export/locale/kz/LC_MESSAGES/django.po
import_export/locale/nl/LC_MESSAGES/django.mo
import_export/locale/nl/LC_MESSAGES/django.po
django_import_export-4.3.11.dist-info/METADATA
django_import_export-4.3.11.dist-info/WHEEL
django_import_export-4.3.11.dist-info/top_level.txt
django_import_export-4.3.11.dist-info/RECORD
