Metadata-Version: 2.4
Name: django-import-export
Version: 4.3.11
Summary: Django application and library for importing and exporting data with included admin integration.
Author-email: Bojan Mihelač <djangoimportexport@gmail.com>
Maintainer-email: Matthew Hegarty <djangoimportexport@gmail.com>
License: Copyright (c) Bojan Mihelac and individual contributors.
Project-URL: Documentation, https://django-import-export.readthedocs.io/en/stable/
Project-URL: Repository, https://github.com/django-import-export/django-import-export
Project-URL: Changelog, https://github.com/django-import-export/django-import-export/blob/main/docs/changelog.rst
Keywords: django,import,export
Platform: OS Independent
Classifier: Framework :: Django
Classifier: Framework :: Django :: 4.2
Classifier: Framework :: Django :: 5.1
Classifier: Framework :: Django :: 5.2
Classifier: Intended Audience :: Developers
Classifier: License :: OSI Approved :: BSD License
Classifier: Operating System :: OS Independent
Classifier: Programming Language :: Python
Classifier: Programming Language :: Python :: 3
Classifier: Programming Language :: Python :: 3.9
Classifier: Programming Language :: Python :: 3.10
Classifier: Programming Language :: Python :: 3.11
Classifier: Programming Language :: Python :: 3.12
Classifier: Programming Language :: Python :: 3.13
Classifier: Programming Language :: Python :: 3 :: Only
Classifier: Topic :: Software Development
Requires-Python: >=3.9
License-File: LICENSE
License-File: AUTHORS
Requires-Dist: diff-match-patch==20241021
Requires-Dist: Django>=4.2
Requires-Dist: tablib>=3.7.0
Provides-Extra: all
Requires-Dist: tablib[all]; extra == "all"
Provides-Extra: cli
Requires-Dist: tablib[cli]; extra == "cli"
Provides-Extra: ods
Requires-Dist: tablib[ods]; extra == "ods"
Provides-Extra: pandas
Requires-Dist: tablib[pandas]; extra == "pandas"
Provides-Extra: xls
Requires-Dist: tablib[xls]; extra == "xls"
Provides-Extra: xlsx
Requires-Dist: tablib[xlsx]; extra == "xlsx"
Provides-Extra: yaml
Requires-Dist: tablib[yaml]; extra == "yaml"
Provides-Extra: docs
Requires-Dist: sphinx==8.1.3; extra == "docs"
Requires-Dist: sphinx-rtd-theme==3.0.1; extra == "docs"
Requires-Dist: openpyxl==3.1.5; extra == "docs"
Requires-Dist: psycopg[binary]>=3.2.9; extra == "docs"
Provides-Extra: tests
Requires-Dist: psycopg[binary]>=3.2.9; extra == "tests"
Requires-Dist: mysqlclient==2.2.5; extra == "tests"
Requires-Dist: chardet==5.2.0; extra == "tests"
Requires-Dist: pytz==2024.2; extra == "tests"
Requires-Dist: memory-profiler==0.61.0; extra == "tests"
Requires-Dist: django-extensions==3.2.3; extra == "tests"
Requires-Dist: coverage==7.6.4; extra == "tests"
Requires-Dist: tablib[all]>=3.7.0; extra == "tests"
Requires-Dist: setuptools-scm==8.1.0; extra == "tests"
Dynamic: license-file
